{
  "Name": "Small Spruce",
  "Group": null,
  "IsElement": true,
  "Offsets": [
    {
      "I": 0,
      "X": -1,
      "Y": 2
    },
    {
      "I": 1,
      "X": 0,
      "Y": 2
    },
    {
      "I": 2,
      "X": 1,
      "Y": 2
    },
    
    
    
    {
      "I": 3,
      "X": -1,
      "Y": 1
    },
    {
      "I": 4,
      "X": 0,
      "Y": 1
    },
    {
      "I": 5,
      "X": 1,
      "Y": 1
    },



    {
      "I": 6,
      "X": -1,
      "Y": 0
    },
    {
      "I": 7,
      "X": 0,
      "Y": 0
    },
    {
      "I": 8,
      "X": 1,
      "Y": 0
    }
  ]
}